[
  {
    "year": 2004,
    "pdf_url": "https://www.courts.nh.gov/sites/g/files/ehbemt471/files/documents/2022-06/2004148starr.pdf",
    "case_name": "DARREN STARR v. GOVERNOR, STATE OF NH",
    "case_number": "2004-292",
    "citation": null,
    "opinion_type": "opinion",
    "date_issued": null,
    "pdf_local_path": "C:\\Users\\gmalb\\Downloads\\nh-supreme-court\\data\\raw\\pdfs\\2004\\2004148starr.pdf"
  },
  {
    "year": 2004,
    "pdf_url": "https://www.courts.nh.gov/sites/g/files/ehbemt471/files/documents/2022-06/2004145nordic.pdf",
    "case_name": "NORDIC INN CONDOMINIUM OWNERS' ASSOCIATION v. ARLINE A. VENTULLO D/B/A NORDIC INN TOO",
    "case_number": "2003-792",
    "citation": null,
    "opinion_type": "opinion",
    "date_issued": null,
    "pdf_local_path": "C:\\Users\\gmalb\\Downloads\\nh-supreme-court\\data\\raw\\pdfs\\2004\\2004145nordic.pdf"
  },
  {
    "year": 2004,
    "pdf_url": "https://www.courts.nh.gov/sites/g/files/ehbemt471/files/documents/2022-06/2004147fox.pdf",
    "case_name": "LAURA FOX & a. v. TOWN OF GREENLAND & a. TOWN OF NEWINGTON v. TOWN OF GREENLAND & a.",
    "case_number": "2004-103",
    "citation": null,
    "opinion_type": "opinion",
    "date_issued": null,
    "pdf_local_path": "C:\\Users\\gmalb\\Downloads\\nh-supreme-court\\data\\raw\\pdfs\\2004\\2004147fox.pdf"
  },
  {
    "year": 2004,
    "pdf_url": "https://www.courts.nh.gov/sites/g/files/ehbemt471/files/documents/2022-06/2004149bedford.pdf",
    "case_name": "BEDFORD CHAPTER - CITIZENS FOR A SOUND ECONOMY & a. v. SCHOOL ADMINISTRATIVE UNIT #25",
    "case_number": "2004-439",
    "citation": null,
    "opinion_type": "opinion",
    "date_issued": null,
    "pdf_local_path": "C:\\Users\\gmalb\\Downloads\\nh-supreme-court\\data\\raw\\pdfs\\2004\\2004149bedford.pdf"
  },
  {
    "year": 2004,
    "pdf_url": "https://www.courts.nh.gov/sites/g/files/ehbemt471/files/documents/2022-06/2004146benson.pdf",
    "case_name": "RICHARD BENSON, M.D. & a. v. NH INSURANCE GUARANTY ASSOCIATION",
    "case_number": "2004-052",
    "citation": null,
    "opinion_type": "opinion",
    "date_issued": null,
    "pdf_local_path": "C:\\Users\\gmalb\\Downloads\\nh-supreme-court\\data\\raw\\pdfs\\2004\\2004146benson.pdf"
  },
  {
    "year": 2004,
    "pdf_url": "https://www.courts.nh.gov/sites/g/files/ehbemt471/files/documents/2022-06/2004142carbo.pdf",
    "case_name": "STATE OF NH v. WILLIAM CARBO",
    "case_number": "2002-762",
    "citation": null,
    "opinion_type": "opinion",
    "date_issued": null,
    "pdf_local_path": "C:\\Users\\gmalb\\Downloads\\nh-supreme-court\\data\\raw\\pdfs\\2004\\2004142carbo.pdf"
  },
  {
    "year": 2004,
    "pdf_url": "https://www.courts.nh.gov/sites/g/files/ehbemt471/files/documents/2022-06/2004144franklin.pdf",
    "case_name": "APPEAL OF FRANKLIN LODGE OF ELKS #1280 BPOE",
    "case_number": "2004-094",
    "citation": null,
    "opinion_type": "opinion",
    "date_issued": null,
    "pdf_local_path": "C:\\Users\\gmalb\\Downloads\\nh-supreme-court\\data\\raw\\pdfs\\2004\\2004144franklin.pdf"
  },
  {
    "year": 2004,
    "pdf_url": "https://www.courts.nh.gov/sites/g/files/ehbemt471/files/documents/2022-06/2004143mailloux.pdf",
    "case_name": "RICHARD L. MAILLOUX v. TOWN OF LONDONDERRY",
    "case_number": "2003-790",
    "citation": null,
    "opinion_type": "opinion",
    "date_issued": null,
    "pdf_local_path": "C:\\Users\\gmalb\\Downloads\\nh-supreme-court\\data\\raw\\pdfs\\2004\\2004143mailloux.pdf"
  },
  {
    "year": 2004,
    "pdf_url": "https://www.courts.nh.gov/sites/g/files/ehbemt471/files/documents/2022-06/2004139ierney.pdf",
    "case_name": "ALFRED CARBONE v. NANCY S. TIERNEY, ESQUIRE",
    "case_number": "2003-321",
    "citation": null,
    "opinion_type": "opinion",
    "date_issued": null,
    "pdf_local_path": "C:\\Users\\gmalb\\Downloads\\nh-supreme-court\\data\\raw\\pdfs\\2004\\2004139ierney.pdf"
  },
  {
    "year": 2004,
    "pdf_url": "https://www.courts.nh.gov/sites/g/files/ehbemt471/files/documents/2022-06/2004141white.pdf",
    "case_name": "DR. LELAND WHITE & a. v. ASPLUNDH TREE EXPERT COMPANY",
    "case_number": "2004-257",
    "citation": null,
    "opinion_type": "opinion",
    "date_issued": null,
    "pdf_local_path": "C:\\Users\\gmalb\\Downloads\\nh-supreme-court\\data\\raw\\pdfs\\2004\\2004141white.pdf"
  },
  {
    "year": 2004,
    "pdf_url": "https://www.courts.nh.gov/sites/g/files/ehbemt471/files/documents/2022-06/2004140watson.pdf",
    "case_name": "STATE OF NH v. KENDALL WATSON",
    "case_number": "2003-821",
    "citation": null,
    "opinion_type": "opinion",
    "date_issued": null,
    "pdf_local_path": "C:\\Users\\gmalb\\Downloads\\nh-supreme-court\\data\\raw\\pdfs\\2004\\2004140watson.pdf"
  },
  {
    "year": 2004,
    "pdf_url": "https://www.courts.nh.gov/sites/g/files/ehbemt471/files/documents/2022-06/20041378prague.pdf",
    "case_name": "BOSTON AND MAINE CORPORATION v. SPRAGUE ENERGY CORPORATION",
    "case_number": "2003-747",
    "citation": null,
    "opinion_type": "opinion",
    "date_issued": null,
    "pdf_local_path": "C:\\Users\\gmalb\\Downloads\\nh-supreme-court\\data\\raw\\pdfs\\2004\\20041378prague.pdf"
  },
  {
    "year": 2004,
    "pdf_url": "https://www.courts.nh.gov/sites/g/files/ehbemt471/files/documents/2022-06/2004137franklin.pdf",
    "case_name": "PETER FRANKLIN v. TOWN OF NEWPORT",
    "case_number": "2004-211",
    "citation": null,
    "opinion_type": "opinion",
    "date_issued": null,
    "pdf_local_path": "C:\\Users\\gmalb\\Downloads\\nh-supreme-court\\data\\raw\\pdfs\\2004\\2004137franklin.pdf"
  },
  {
    "year": 2004,
    "pdf_url": "https://www.courts.nh.gov/sites/g/files/ehbemt471/files/documents/2022-06/2004134anthony.pdf",
    "case_name": "STATE OF NH v. VIRGINIA ANTHONY",
    "case_number": "2003-728",
    "citation": null,
    "opinion_type": "opinion",
    "date_issued": null,
    "pdf_local_path": "C:\\Users\\gmalb\\Downloads\\nh-supreme-court\\data\\raw\\pdfs\\2004\\2004134anthony.pdf"
  },
  {
    "year": 2004,
    "pdf_url": "https://www.courts.nh.gov/sites/g/files/ehbemt471/files/documents/2022-06/2004136healthtrust.pdf",
    "case_name": "PROFESSIONAL FIREFIGHTERS OF NH v. HEALTHTRUST, INC.",
    "case_number": "2004-017",
    "citation": null,
    "opinion_type": "opinion",
    "date_issued": null,
    "pdf_local_path": "C:\\Users\\gmalb\\Downloads\\nh-supreme-court\\data\\raw\\pdfs\\2004\\2004136healthtrust.pdf"
  },
  {
    "year": 2004,
    "pdf_url": "https://www.courts.nh.gov/sites/g/files/ehbemt471/files/documents/2022-06/2004133thayer.pdf",
    "case_name": "NATHANIEL S. THAYER v. TOWN OF TILTON",
    "case_number": "2003-421",
    "citation": null,
    "opinion_type": "opinion",
    "date_issued": null,
    "pdf_local_path": "C:\\Users\\gmalb\\Downloads\\nh-supreme-court\\data\\raw\\pdfs\\2004\\2004133thayer.pdf"
  },
  {
    "year": 2004,
    "pdf_url": "https://www.courts.nh.gov/sites/g/files/ehbemt471/files/documents/2022-06/2004135edwards.pdf",
    "case_name": "RAL AUTOMOTIVE GROUP, INC. v. JAY C. EDWARDS",
    "case_number": "2003-771",
    "citation": null,
    "opinion_type": "opinion",
    "date_issued": null,
    "pdf_local_path": "C:\\Users\\gmalb\\Downloads\\nh-supreme-court\\data\\raw\\pdfs\\2004\\2004135edwards.pdf"
  },
  {
    "year": 2004,
    "pdf_url": "https://www.courts.nh.gov/sites/g/files/ehbemt471/files/documents/2022-06/2004132hopkinton.pdf",
    "case_name": "APPEAL OF HOPKINTON SCHOOL DISTRICT",
    "case_number": "2003-667",
    "citation": null,
    "opinion_type": "opinion",
    "date_issued": null,
    "pdf_local_path": "C:\\Users\\gmalb\\Downloads\\nh-supreme-court\\data\\raw\\pdfs\\2004\\2004132hopkinton.pdf"
  },
  {
    "year": 2004,
    "pdf_url": "https://www.courts.nh.gov/sites/g/files/ehbemt471/files/documents/2022-06/2004131rymes.pdf",
    "case_name": "RYMES HEATING OILS, INC. v. COMMISSIONER, NH DEPARTMENT OF SAFETY",
    "case_number": "2003-519",
    "citation": null,
    "opinion_type": "opinion",
    "date_issued": null,
    "pdf_local_path": "C:\\Users\\gmalb\\Downloads\\nh-supreme-court\\data\\raw\\pdfs\\2004\\2004131rymes.pdf"
  },
  {
    "year": 2004,
    "pdf_url": "https://www.courts.nh.gov/sites/g/files/ehbemt471/files/documents/2022-06/2004130mcintyre.pdf",
    "case_name": "STATE OF NH v. JEREMY McINTYRE",
    "case_number": "2003-395",
    "citation": null,
    "opinion_type": "opinion",
    "date_issued": null,
    "pdf_local_path": "C:\\Users\\gmalb\\Downloads\\nh-supreme-court\\data\\raw\\pdfs\\2004\\2004130mcintyre.pdf"
  },
  {
    "year": 2004,
    "pdf_url": "https://www.courts.nh.gov/sites/g/files/ehbemt471/files/documents/2022-06/2004128treloar.pdf",
    "case_name": "IN RE ESTATE OF JOSIAH JAMES TRELOAR, JR. a/k/a J. JAMES TRELOAR",
    "case_number": "2004-163",
    "citation": null,
    "opinion_type": "opinion",
    "date_issued": null,
    "pdf_local_path": "C:\\Users\\gmalb\\Downloads\\nh-supreme-court\\data\\raw\\pdfs\\2004\\2004128treloar.pdf"
  },
  {
    "year": 2004,
    "pdf_url": "https://www.courts.nh.gov/sites/g/files/ehbemt471/files/documents/2022-06/2004127moran.pdf",
    "case_name": "STATE OF NH v. JAMES MORAN",
    "case_number": "2003-804",
    "citation": null,
    "opinion_type": "opinion",
    "date_issued": null,
    "pdf_local_path": "C:\\Users\\gmalb\\Downloads\\nh-supreme-court\\data\\raw\\pdfs\\2004\\2004127moran.pdf"
  },
  {
    "year": 2004,
    "pdf_url": "https://www.courts.nh.gov/sites/g/files/ehbemt471/files/documents/2022-06/2004129richard.pdf",
    "case_name": "DEBBIE RICHARD & a. v. PEMBROKE SCHOOL DISTRICT",
    "case_number": "2004-064",
    "citation": null,
    "opinion_type": "opinion",
    "date_issued": null,
    "pdf_local_path": "C:\\Users\\gmalb\\Downloads\\nh-supreme-court\\data\\raw\\pdfs\\2004\\2004129richard.pdf"
  },
  {
    "year": 2004,
    "pdf_url": "https://www.courts.nh.gov/sites/g/files/ehbemt471/files/documents/2022-06/2004126beauregard.pdf",
    "case_name": "PETITION OF CHARLES R. BEAUREGARD, JR. & a.",
    "case_number": "2004-005",
    "citation": null,
    "opinion_type": "opinion",
    "date_issued": null,
    "pdf_local_path": "C:\\Users\\gmalb\\Downloads\\nh-supreme-court\\data\\raw\\pdfs\\2004\\2004126beauregard.pdf"
  },
  {
    "year": 2004,
    "pdf_url": "https://www.courts.nh.gov/sites/g/files/ehbemt471/files/documents/2022-06/2004124thomas.pdf",
    "case_name": "TERRY T. THOMAS v. THE TELEGRAPH PUBLISHING CO. d/b/a THE TELEGRAPH & a.",
    "case_number": "2003-700",
    "citation": null,
    "opinion_type": "opinion",
    "date_issued": null,
    "pdf_local_path": "C:\\Users\\gmalb\\Downloads\\nh-supreme-court\\data\\raw\\pdfs\\2004\\2004124thomas.pdf"
  },
  {
    "year": 2004,
    "pdf_url": "https://www.courts.nh.gov/sites/g/files/ehbemt471/files/documents/2022-06/2004122brobst.pdf",
    "case_name": "STATE OF NH v. MICHAEL B. BROBST",
    "case_number": "2003-503",
    "citation": null,
    "opinion_type": "opinion",
    "date_issued": null,
    "pdf_local_path": "C:\\Users\\gmalb\\Downloads\\nh-supreme-court\\data\\raw\\pdfs\\2004\\2004122brobst.pdf"
  },
  {
    "year": 2004,
    "pdf_url": "https://www.courts.nh.gov/sites/g/files/ehbemt471/files/documents/2022-06/2004121carignan.pdf",
    "case_name": "MARY CARIGNAN v. NH INTERNATIONAL SPEEDWAY, INC.",
    "case_number": "2003-407",
    "citation": null,
    "opinion_type": "opinion",
    "date_issued": null,
    "pdf_local_path": "C:\\Users\\gmalb\\Downloads\\nh-supreme-court\\data\\raw\\pdfs\\2004\\2004121carignan.pdf"
  },
  {
    "year": 2004,
    "pdf_url": "https://www.courts.nh.gov/sites/g/files/ehbemt471/files/documents/2022-06/2004123king.pdf",
    "case_name": "IN RE ESTATE OF J. DOUGLAS KING",
    "case_number": "2003-829",
    "citation": null,
    "opinion_type": "opinion",
    "date_issued": null,
    "pdf_local_path": "C:\\Users\\gmalb\\Downloads\\nh-supreme-court\\data\\raw\\pdfs\\2004\\2004123king.pdf"
  },
  {
    "year": 2004,
    "pdf_url": "https://www.courts.nh.gov/sites/g/files/ehbemt471/files/documents/2022-06/2004119acworth.pdf",
    "case_name": "TOWN OF ACWORTH & a. v. FALL MOUNTAIN REGIONAL SCHOOL DISTRICT",
    "case_number": "2003-791",
    "citation": null,
    "opinion_type": "opinion",
    "date_issued": null,
    "pdf_local_path": "C:\\Users\\gmalb\\Downloads\\nh-supreme-court\\data\\raw\\pdfs\\2004\\2004119acworth.pdf"
  },
  {
    "year": 2004,
    "pdf_url": "https://www.courts.nh.gov/sites/g/files/ehbemt471/files/documents/2022-06/2004120dewyngaerdt.pdf",
    "case_name": "MARK DEWYNGAERDT d/b/a SUPERIOR TREE SERVICE & a. v. BEAN INSURANCE AGENCY, INC.",
    "case_number": "2004-025",
    "citation": null,
    "opinion_type": "opinion",
    "date_issued": null,
    "pdf_local_path": "C:\\Users\\gmalb\\Downloads\\nh-supreme-court\\data\\raw\\pdfs\\2004\\2004120dewyngaerdt.pdf"
  },
  {
    "year": 2004,
    "pdf_url": "https://www.courts.nh.gov/sites/g/files/ehbemt471/files/documents/2022-06/2004117tiberghein.pdf",
    "case_name": "CHARLES TIBERGHEIN & a. v. B.R. JONES ROOFING COMPANY",
    "case_number": "2003-564",
    "citation": null,
    "opinion_type": "opinion",
    "date_issued": null,
    "pdf_local_path": "C:\\Users\\gmalb\\Downloads\\nh-supreme-court\\data\\raw\\pdfs\\2004\\2004117tiberghein.pdf"
  },
  {
    "year": 2004,
    "pdf_url": "https://www.courts.nh.gov/sites/g/files/ehbemt471/files/documents/2022-06/2004116flynn.pdf",
    "case_name": "STATE OF NH v. JOHN FLYNN",
    "case_number": "2003-470",
    "citation": null,
    "opinion_type": "opinion",
    "date_issued": null,
    "pdf_local_path": "C:\\Users\\gmalb\\Downloads\\nh-supreme-court\\data\\raw\\pdfs\\2004\\2004116flynn.pdf"
  },
  {
    "year": 2004,
    "pdf_url": "https://www.courts.nh.gov/sites/g/files/ehbemt471/files/documents/2022-06/2004114follansbee.pdf",
    "case_name": "DAVID FOLLANSBEE v. PLYMOUTH DISTRICT COURT; RICHARD KELLY v. STATE OF NH",
    "case_number": "2003-473",
    "citation": null,
    "opinion_type": "opinion",
    "date_issued": null,
    "pdf_local_path": "C:\\Users\\gmalb\\Downloads\\nh-supreme-court\\data\\raw\\pdfs\\2004\\2004114follansbee.pdf"
  },
  {
    "year": 2004,
    "pdf_url": "https://www.courts.nh.gov/sites/g/files/ehbemt471/files/documents/2022-06/2004108hofland.pdf",
    "case_name": "STATE OF NH v. RANDALL B. HOFLAND",
    "case_number": "2003-265",
    "citation": null,
    "opinion_type": "opinion",
    "date_issued": null,
    "pdf_local_path": "C:\\Users\\gmalb\\Downloads\\nh-supreme-court\\data\\raw\\pdfs\\2004\\2004108hofland.pdf"
  },
  {
    "year": 2004,
    "pdf_url": "https://www.courts.nh.gov/sites/g/files/ehbemt471/files/documents/2022-06/2004098verizon.pdf",
    "case_name": "VERIZON NEW ENGLAND, INC. V. CITY OF ROCHESTER",
    "case_number": "2003-572",
    "citation": null,
    "opinion_type": "opinion",
    "date_issued": null,
    "pdf_local_path": "C:\\Users\\gmalb\\Downloads\\nh-supreme-court\\data\\raw\\pdfs\\2004\\2004098verizon.pdf"
  },
  {
    "year": 2004,
    "pdf_url": "https://www.courts.nh.gov/sites/g/files/ehbemt471/files/documents/2022-06/2004100linehan.pdf",
    "case_name": "J. DANIEL LINEHAN, HIGH SHERIFF V. ROCKINGHAM COUNTY COMMISSIONERS",
    "case_number": "2003-826",
    "citation": null,
    "opinion_type": "opinion",
    "date_issued": null,
    "pdf_local_path": "C:\\Users\\gmalb\\Downloads\\nh-supreme-court\\data\\raw\\pdfs\\2004\\2004100linehan.pdf"
  },
  {
    "year": 2004,
    "pdf_url": "https://www.courts.nh.gov/sites/g/files/ehbemt471/files/documents/2022-06/2004097cook.pdf",
    "case_name": "IN THE MATTER OF DENISE ANGLEY-COOK AND JOHN W. COOK",
    "case_number": "2003-514",
    "citation": null,
    "opinion_type": "opinion",
    "date_issued": null,
    "pdf_local_path": "C:\\Users\\gmalb\\Downloads\\nh-supreme-court\\data\\raw\\pdfs\\2004\\2004097cook.pdf"
  },
  {
    "year": 2004,
    "pdf_url": "https://www.courts.nh.gov/sites/g/files/ehbemt471/files/documents/2022-06/2004099fogg.pdf",
    "case_name": "IN THE MATTER OF MICHELLE (FOGG) GLAUDE AND KENNETH FOGG, II",
    "case_number": "2003-694",
    "citation": null,
    "opinion_type": "opinion",
    "date_issued": null,
    "pdf_local_path": "C:\\Users\\gmalb\\Downloads\\nh-supreme-court\\data\\raw\\pdfs\\2004\\2004099fogg.pdf"
  },
  {
    "year": 2004,
    "pdf_url": "https://www.courts.nh.gov/sites/g/files/ehbemt471/files/documents/2022-06/2004096bulman.pdf",
    "case_name": "WHITE CLIFFS AT DOVER V. ELAINE BULMAN",
    "case_number": "2003-454",
    "citation": null,
    "opinion_type": "opinion",
    "date_issued": null,
    "pdf_local_path": "C:\\Users\\gmalb\\Downloads\\nh-supreme-court\\data\\raw\\pdfs\\2004\\2004096bulman.pdf"
  },
  {
    "year": 2004,
    "pdf_url": "https://www.courts.nh.gov/sites/g/files/ehbemt471/files/documents/2022-06/2004093sweeney.pdf",
    "case_name": "ALAINA SWEENEY v. RAGGED MT. SKI AREA, INC.",
    "case_number": "2003-719",
    "citation": null,
    "opinion_type": "opinion",
    "date_issued": null,
    "pdf_local_path": "C:\\Users\\gmalb\\Downloads\\nh-supreme-court\\data\\raw\\pdfs\\2004\\2004093sweeney.pdf"
  },
  {
    "year": 2004,
    "pdf_url": "https://www.courts.nh.gov/sites/g/files/ehbemt471/files/documents/2022-06/2004095bean.pdf",
    "case_name": "CLAUDETTE BEAN v. RED OAK PROPERTY MANAGEMENT",
    "case_number": "2004-026",
    "citation": null,
    "opinion_type": "opinion",
    "date_issued": null,
    "pdf_local_path": "C:\\Users\\gmalb\\Downloads\\nh-supreme-court\\data\\raw\\pdfs\\2004\\2004095bean.pdf"
  },
  {
    "year": 2004,
    "pdf_url": "https://www.courts.nh.gov/sites/g/files/ehbemt471/files/documents/2022-06/2004092hearns.pdf",
    "case_name": "STATE OF NH v. DWAYNE HEARNS",
    "case_number": "2003-314",
    "citation": null,
    "opinion_type": "opinion",
    "date_issued": null,
    "pdf_local_path": "C:\\Users\\gmalb\\Downloads\\nh-supreme-court\\data\\raw\\pdfs\\2004\\2004092hearns.pdf"
  },
  {
    "year": 2004,
    "pdf_url": "https://www.courts.nh.gov/sites/g/files/ehbemt471/files/documents/2022-06/2004094nadler.pdf",
    "case_name": "STATE OF NH v. ALLEN NADLER",
    "case_number": "2003-835",
    "citation": null,
    "opinion_type": "opinion",
    "date_issued": null,
    "pdf_local_path": "C:\\Users\\gmalb\\Downloads\\nh-supreme-court\\data\\raw\\pdfs\\2004\\2004094nadler.pdf"
  },
  {
    "year": 2004,
    "pdf_url": "https://www.courts.nh.gov/sites/g/files/ehbemt471/files/documents/2022-06/2004091shopland.pdf",
    "case_name": "RUSSELL SHOPLAND & a. v. TOWN OF ENFIELD",
    "case_number": "2002-812",
    "citation": null,
    "opinion_type": "opinion",
    "date_issued": null,
    "pdf_local_path": "C:\\Users\\gmalb\\Downloads\\nh-supreme-court\\data\\raw\\pdfs\\2004\\2004091shopland.pdf"
  },
  {
    "year": 2004,
    "pdf_url": "https://www.courts.nh.gov/sites/g/files/ehbemt471/files/documents/2022-06/2004088beaudoin.pdf",
    "case_name": "190 ELM STREET REALTY, LLC v. HANNAH CAMERY BEAUDOIN",
    "case_number": "2003-451",
    "citation": null,
    "opinion_type": "opinion",
    "date_issued": null,
    "pdf_local_path": "C:\\Users\\gmalb\\Downloads\\nh-supreme-court\\data\\raw\\pdfs\\2004\\2004088beaudoin.pdf"
  },
  {
    "year": 2004,
    "pdf_url": "https://www.courts.nh.gov/sites/g/files/ehbemt471/files/documents/2022-06/2004090steels.pdf",
    "case_name": "2003-689, NEW HAMPSHIRE WATER RESOURCES COUNCIL v. STEELS POND HYDRO, INC. & a.",
    "case_number": "2003-669",
    "citation": null,
    "opinion_type": "opinion",
    "date_issued": null,
    "pdf_local_path": "C:\\Users\\gmalb\\Downloads\\nh-supreme-court\\data\\raw\\pdfs\\2004\\2004090steels.pdf"
  },
  {
    "year": 2004,
    "pdf_url": "https://www.courts.nh.gov/sites/g/files/ehbemt471/files/documents/2022-06/2004089whitney.pdf",
    "case_name": "IN THE MATTER OF DIANNE (WHITNEY) HENNESSEY-MARTIN AND MICHAEL J. WHITNEY",
    "case_number": "2003-531",
    "citation": null,
    "opinion_type": "opinion",
    "date_issued": null,
    "pdf_local_path": "C:\\Users\\gmalb\\Downloads\\nh-supreme-court\\data\\raw\\pdfs\\2004\\2004089whitney.pdf"
  },
  {
    "year": 2004,
    "pdf_url": "https://www.courts.nh.gov/sites/g/files/ehbemt471/files/documents/2022-06/2004087leonard.pdf",
    "case_name": "THE STATE OF NEW HAMPSHIRE v. PETER LEONARD",
    "case_number": "2003-406",
    "citation": null,
    "opinion_type": "opinion",
    "date_issued": null,
    "pdf_local_path": "C:\\Users\\gmalb\\Downloads\\nh-supreme-court\\data\\raw\\pdfs\\2004\\2004087leonard.pdf"
  },
  {
    "year": 2004,
    "pdf_url": "https://www.courts.nh.gov/sites/g/files/ehbemt471/files/documents/2022-06/2004086smalley.pdf",
    "case_name": "THE STATE OF NEW HAMPSHIRE v. ERIC SMALLEY",
    "case_number": "2003-198",
    "citation": null,
    "opinion_type": "opinion",
    "date_issued": null,
    "pdf_local_path": "C:\\Users\\gmalb\\Downloads\\nh-supreme-court\\data\\raw\\pdfs\\2004\\2004086smalley.pdf"
  },
  {
    "year": 2004,
    "pdf_url": "https://www.courts.nh.gov/sites/g/files/ehbemt471/files/documents/2022-06/2004085zwicker.pdf",
    "case_name": "THE STATE OF NEW HAMPSHIRE v. TROY W. ZWICKER",
    "case_number": "2003-082",
    "citation": null,
    "opinion_type": "opinion",
    "date_issued": null,
    "pdf_local_path": "C:\\Users\\gmalb\\Downloads\\nh-supreme-court\\data\\raw\\pdfs\\2004\\2004085zwicker.pdf"
  },
  {
    "year": 2004,
    "pdf_url": "https://www.courts.nh.gov/sites/g/files/ehbemt471/files/documents/2022-05/2004084portsmouth.pdf",
    "case_name": "APPEAL OF THE CITY OF PORTSMOUTH (New Hampshire Board of Tax and Land Appeals)",
    "case_number": "2003-547",
    "citation": null,
    "opinion_type": "opinion",
    "date_issued": null,
    "pdf_local_path": "C:\\Users\\gmalb\\Downloads\\nh-supreme-court\\data\\raw\\pdfs\\2004\\2004084portsmouth.pdf"
  },
  {
    "year": 2004,
    "pdf_url": "https://www.courts.nh.gov/sites/g/files/ehbemt471/files/documents/2022-05/2004083dowman.pdf",
    "case_name": "THE STATE OF NEW HAMPSHIRE v. STEPHEN DOWMAN",
    "case_number": "2003-422",
    "citation": null,
    "opinion_type": "opinion",
    "date_issued": null,
    "pdf_local_path": "C:\\Users\\gmalb\\Downloads\\nh-supreme-court\\data\\raw\\pdfs\\2004\\2004083dowman.pdf"
  },
  {
    "year": 2004,
    "pdf_url": "https://www.courts.nh.gov/sites/g/files/ehbemt471/files/documents/2022-05/2004082ellsworth.pdf",
    "case_name": "THE STATE OF NEW HAMPSHIRE v. RICHARD ELLSWORTH",
    "case_number": "2003-354",
    "citation": null,
    "opinion_type": "opinion",
    "date_issued": null,
    "pdf_local_path": "C:\\Users\\gmalb\\Downloads\\nh-supreme-court\\data\\raw\\pdfs\\2004\\2004082ellsworth.pdf"
  },
  {
    "year": 2004,
    "pdf_url": "https://www.courts.nh.gov/sites/g/files/ehbemt471/files/documents/2022-05/2004081clifton.pdf",
    "case_name": "PETITION OF SENATOR CLIFTON BELOW & a.",
    "case_number": "2004-361",
    "citation": null,
    "opinion_type": "opinion",
    "date_issued": null,
    "pdf_local_path": "C:\\Users\\gmalb\\Downloads\\nh-supreme-court\\data\\raw\\pdfs\\2004\\2004081clifton.pdf"
  },
  {
    "year": 2004,
    "pdf_url": "https://www.courts.nh.gov/sites/g/files/ehbemt471/files/documents/2022-05/2004080bennett.pdf",
    "case_name": "PETITION OF TERRY M. BENNETT (New Hampshire Insurance Department)",
    "case_number": "2003-607",
    "citation": null,
    "opinion_type": "opinion",
    "date_issued": null,
    "pdf_local_path": "C:\\Users\\gmalb\\Downloads\\nh-supreme-court\\data\\raw\\pdfs\\2004\\2004080bennett.pdf"
  },
  {
    "year": 2004,
    "pdf_url": "https://www.courts.nh.gov/sites/g/files/ehbemt471/files/documents/2022-05/2004079judicial.pdf",
    "case_name": "PETITION OF THE JUDICIAL CONDUCT COMMITTEE",
    "case_number": "2003-798",
    "citation": null,
    "opinion_type": "opinion",
    "date_issued": null,
    "pdf_local_path": "C:\\Users\\gmalb\\Downloads\\nh-supreme-court\\data\\raw\\pdfs\\2004\\2004079judicial.pdf"
  },
  {
    "year": 2004,
    "pdf_url": "https://www.courts.nh.gov/sites/g/files/ehbemt471/files/documents/2022-05/2004078barassociation.pdf",
    "case_name": "PETITION OF NEW HAMPSHIRE BAR ASSOCIATION",
    "case_number": "2003-482",
    "citation": null,
    "opinion_type": "opinion",
    "date_issued": null,
    "pdf_local_path": "C:\\Users\\gmalb\\Downloads\\nh-supreme-court\\data\\raw\\pdfs\\2004\\2004078barassociation.pdf"
  },
  {
    "year": 2004,
    "pdf_url": "https://www.courts.nh.gov/sites/g/files/ehbemt471/files/documents/2022-05/2004077arabian.pdf",
    "case_name": "IN THE MATTER OF HAROLD ARABIAN AND DENISE SQUILLANTE (ARABIAN)",
    "case_number": "2003-580",
    "citation": null,
    "opinion_type": "opinion",
    "date_issued": null,
    "pdf_local_path": "C:\\Users\\gmalb\\Downloads\\nh-supreme-court\\data\\raw\\pdfs\\2004\\2004077arabian.pdf"
  },
  {
    "year": 2004,
    "pdf_url": "https://www.courts.nh.gov/sites/g/files/ehbemt471/files/documents/2022-05/2004076barnesorder.pdf",
    "case_name": "ORDER, 2003-039, THE STATE OF NEW HAMPSHIRE v. DANIEL BARNES",
    "case_number": null,
    "citation": null,
    "opinion_type": "opinion",
    "date_issued": null,
    "pdf_local_path": "C:\\Users\\gmalb\\Downloads\\nh-supreme-court\\data\\raw\\pdfs\\2004\\2004076barnesorder.pdf"
  },
  {
    "year": 2004,
    "pdf_url": "https://www.courts.nh.gov/sites/g/files/ehbemt471/files/documents/2022-05/2004076barnes.pdf",
    "case_name": "THE STATE OF NEW HAMPSHIRE v. DANIEL BARNES ORIGINALLY ISSUED APRIL 16, 2004",
    "case_number": "2003-039",
    "citation": null,
    "opinion_type": "opinion",
    "date_issued": null,
    "pdf_local_path": "C:\\Users\\gmalb\\Downloads\\nh-supreme-court\\data\\raw\\pdfs\\2004\\2004076barnes.pdf"
  },
  {
    "year": 2004,
    "pdf_url": "https://www.courts.nh.gov/sites/g/files/ehbemt471/files/documents/2022-05/2004074chesbrough.pdf",
    "case_name": "THE STATE OF NEW HAMPSHIRE v. ADAM CHESBROUGH",
    "case_number": "2002-366",
    "citation": null,
    "opinion_type": "opinion",
    "date_issued": null,
    "pdf_local_path": "C:\\Users\\gmalb\\Downloads\\nh-supreme-court\\data\\raw\\pdfs\\2004\\2004074chesbrough.pdf"
  },
  {
    "year": 2004,
    "pdf_url": "https://www.courts.nh.gov/sites/g/files/ehbemt471/files/documents/2022-05/2004075martin.pdf",
    "case_name": "THE STATE OF NEW HAMPSHIRE v. RONALD MARTIN",
    "case_number": "2003-529",
    "citation": null,
    "opinion_type": "opinion",
    "date_issued": null,
    "pdf_local_path": "C:\\Users\\gmalb\\Downloads\\nh-supreme-court\\data\\raw\\pdfs\\2004\\2004075martin.pdf"
  },
  {
    "year": 2004,
    "pdf_url": "https://www.courts.nh.gov/sites/g/files/ehbemt471/files/documents/2022-05/2004073blackthorneorder.pdf",
    "case_name": "ORDER, 2003-401, THE BLACKTHORNE GROUP, INC. v. PINES OF NEWMARKET, INC.",
    "case_number": null,
    "citation": null,
    "opinion_type": "opinion",
    "date_issued": null,
    "pdf_local_path": "C:\\Users\\gmalb\\Downloads\\nh-supreme-court\\data\\raw\\pdfs\\2004\\2004073blackthorneorder.pdf"
  },
  {
    "year": 2004,
    "pdf_url": "https://www.courts.nh.gov/sites/g/files/ehbemt471/files/documents/2022-05/2004070hutchins.pdf",
    "case_name": "STEPHEN HUTCHINS & a. v. ROBIN PEABODY & a.",
    "case_number": "2003-368",
    "citation": null,
    "opinion_type": "opinion",
    "date_issued": null,
    "pdf_local_path": "C:\\Users\\gmalb\\Downloads\\nh-supreme-court\\data\\raw\\pdfs\\2004\\2004070hutchins.pdf"
  },
  {
    "year": 2004,
    "pdf_url": "https://www.courts.nh.gov/sites/g/files/ehbemt471/files/documents/2022-05/2004073blackthorne.pdf",
    "case_name": "THE BLACKTHORNE GROUP, INC. v. PINES OF NEWMARKET, INC. ORIGINALLY ISSUED APRIL 21, 2004",
    "case_number": "2003-401",
    "citation": null,
    "opinion_type": "opinion",
    "date_issued": null,
    "pdf_local_path": "C:\\Users\\gmalb\\Downloads\\nh-supreme-court\\data\\raw\\pdfs\\2004\\2004073blackthorne.pdf"
  },
  {
    "year": 2004,
    "pdf_url": "https://www.courts.nh.gov/sites/g/files/ehbemt471/files/documents/2022-05/2004072mckeown.pdf",
    "case_name": "THE STATE OF NEW HAMPSHIRE v. CHRISTOPHER J. MCKEOWN",
    "case_number": "2002-792",
    "citation": null,
    "opinion_type": "opinion",
    "date_issued": null,
    "pdf_local_path": "C:\\Users\\gmalb\\Downloads\\nh-supreme-court\\data\\raw\\pdfs\\2004\\2004072mckeown.pdf"
  },
  {
    "year": 2004,
    "pdf_url": "https://www.courts.nh.gov/sites/g/files/ehbemt471/files/documents/2022-05/2004071boccia.pdf",
    "case_name": "MICHAEL BOCCIA & a. v. CITY OF PORTSMOUTH & a.",
    "case_number": "2003-493",
    "citation": null,
    "opinion_type": "opinion",
    "date_issued": null,
    "pdf_local_path": "C:\\Users\\gmalb\\Downloads\\nh-supreme-court\\data\\raw\\pdfs\\2004\\2004071boccia.pdf"
  },
  {
    "year": 2004,
    "pdf_url": "https://www.courts.nh.gov/sites/g/files/ehbemt471/files/documents/2022-05/2004069summa.pdf",
    "case_name": "SUMMA HUMMA ENTERPRISES, LLC D/B/A MB TRACTOR v. TOWN OF TILTON & a.",
    "case_number": "2003-398",
    "citation": null,
    "opinion_type": "opinion",
    "date_issued": null,
    "pdf_local_path": "C:\\Users\\gmalb\\Downloads\\nh-supreme-court\\data\\raw\\pdfs\\2004\\2004069summa.pdf"
  },
  {
    "year": 2004,
    "pdf_url": "https://www.courts.nh.gov/sites/g/files/ehbemt471/files/documents/2022-05/2004068peerless.pdf",
    "case_name": "PEERLESS INSURANCE & a. v. VERMONT MUTUAL INSURANCE COMPANY & a.",
    "case_number": "2003-164",
    "citation": null,
    "opinion_type": "opinion",
    "date_issued": null,
    "pdf_local_path": "C:\\Users\\gmalb\\Downloads\\nh-supreme-court\\data\\raw\\pdfs\\2004\\2004068peerless.pdf"
  },
  {
    "year": 2004,
    "pdf_url": "https://www.courts.nh.gov/sites/g/files/ehbemt471/files/documents/2022-05/2004066brook.pdf",
    "case_name": "JAMES D. PEDERSEN v. MARCIA A. BROOK",
    "case_number": "2003-533",
    "citation": null,
    "opinion_type": "opinion",
    "date_issued": null,
    "pdf_local_path": "C:\\Users\\gmalb\\Downloads\\nh-supreme-court\\data\\raw\\pdfs\\2004\\2004066brook.pdf"
  },
  {
    "year": 2004,
    "pdf_url": "https://www.courts.nh.gov/sites/g/files/ehbemt471/files/documents/2022-05/2004065king.pdf",
    "case_name": "THE STATE OF NEW HAMPSHIRE v. JOSEPH E. KING",
    "case_number": "2003-512",
    "citation": null,
    "opinion_type": "opinion",
    "date_issued": null,
    "pdf_local_path": "C:\\Users\\gmalb\\Downloads\\nh-supreme-court\\data\\raw\\pdfs\\2004\\2004065king.pdf"
  },
  {
    "year": 2004,
    "pdf_url": "https://www.courts.nh.gov/sites/g/files/ehbemt471/files/documents/2022-05/2004067ireland.pdf",
    "case_name": "THOMAS IRELAND v. TOWN OF CANDIA",
    "case_number": "2003-690",
    "citation": null,
    "opinion_type": "opinion",
    "date_issued": null,
    "pdf_local_path": "C:\\Users\\gmalb\\Downloads\\nh-supreme-court\\data\\raw\\pdfs\\2004\\2004067ireland.pdf"
  },
  {
    "year": 2004,
    "pdf_url": "https://www.courts.nh.gov/sites/g/files/ehbemt471/files/documents/2022-05/2004064clark.pdf",
    "case_name": "THE STATE OF NEW HAMPSHIRE v. LEWIS CLARK",
    "case_number": "2003-249",
    "citation": null,
    "opinion_type": "opinion",
    "date_issued": null,
    "pdf_local_path": "C:\\Users\\gmalb\\Downloads\\nh-supreme-court\\data\\raw\\pdfs\\2004\\2004064clark.pdf"
  },
  {
    "year": 2004,
    "pdf_url": "https://www.courts.nh.gov/sites/g/files/ehbemt471/files/documents/2022-05/2004063porter.pdf",
    "case_name": "MICHAEL PORTER v. CITY OF MANCHESTER & a.",
    "case_number": "2003-099",
    "citation": null,
    "opinion_type": "opinion",
    "date_issued": null,
    "pdf_local_path": "C:\\Users\\gmalb\\Downloads\\nh-supreme-court\\data\\raw\\pdfs\\2004\\2004063porter.pdf"
  },
  {
    "year": 2004,
    "pdf_url": "https://www.courts.nh.gov/sites/g/files/ehbemt471/files/documents/2022-05/2004062andrews.pdf",
    "case_name": "THE STATE OF NEW HAMPSHIRE v. JOSHUA MCKINNON-ANDREWS",
    "case_number": "2003-234",
    "citation": null,
    "opinion_type": "opinion",
    "date_issued": null,
    "pdf_local_path": "C:\\Users\\gmalb\\Downloads\\nh-supreme-court\\data\\raw\\pdfs\\2004\\2004062andrews.pdf"
  },
  {
    "year": 2004,
    "pdf_url": "https://www.courts.nh.gov/sites/g/files/ehbemt471/files/documents/2022-05/2004061juvenile.pdf",
    "case_name": "IN RE JUVENILE 2003-187",
    "case_number": "2003-187",
    "citation": null,
    "opinion_type": "opinion",
    "date_issued": null,
    "pdf_local_path": "C:\\Users\\gmalb\\Downloads\\nh-supreme-court\\data\\raw\\pdfs\\2004\\2004061juvenile.pdf"
  },
  {
    "year": 2004,
    "pdf_url": "https://www.courts.nh.gov/sites/g/files/ehbemt471/files/documents/2022-05/2004060brenes.pdf",
    "case_name": "THE STATE OF NEW HAMPSHIRE v. ALEX BRENES",
    "case_number": "2003-301",
    "citation": null,
    "opinion_type": "opinion",
    "date_issued": null,
    "pdf_local_path": "C:\\Users\\gmalb\\Downloads\\nh-supreme-court\\data\\raw\\pdfs\\2004\\2004060brenes.pdf"
  },
  {
    "year": 2004,
    "pdf_url": "https://www.courts.nh.gov/sites/g/files/ehbemt471/files/documents/2022-05/2004059governor.pdf",
    "case_name": "PETITION OF THE GOVERNOR AND EXECUTIVE COUNCIL",
    "case_number": "2003-0827",
    "citation": null,
    "opinion_type": "opinion",
    "date_issued": null,
    "pdf_local_path": "C:\\Users\\gmalb\\Downloads\\nh-supreme-court\\data\\raw\\pdfs\\2004\\2004059governor.pdf"
  },
  {
    "year": 2004,
    "pdf_url": "https://www.courts.nh.gov/sites/g/files/ehbemt471/files/documents/2022-05/2004057lheureux.pdf",
    "case_name": "THE STATE OF NEW HAMPSHIRE v. LAURENT L'HEUREUX",
    "case_number": "2003-242",
    "citation": null,
    "opinion_type": "opinion",
    "date_issued": null,
    "pdf_local_path": "C:\\Users\\gmalb\\Downloads\\nh-supreme-court\\data\\raw\\pdfs\\2004\\2004057lheureux.pdf"
  },
  {
    "year": 2004,
    "pdf_url": "https://www.courts.nh.gov/sites/g/files/ehbemt471/files/documents/2022-05/2004058energynorth.pdf",
    "case_name": "ENERGYNORTH NATURAL GAS, INC. v. UNDERWRITERS AT LLOYD'S ENERGYNORTH NATURAL GAS, INC. v. UTICA MUTUAL INSURANCE COMPANY & a",
    "case_number": "2003-437",
    "citation": null,
    "opinion_type": "opinion",
    "date_issued": null,
    "pdf_local_path": "C:\\Users\\gmalb\\Downloads\\nh-supreme-court\\data\\raw\\pdfs\\2004\\2004058energynorth.pdf"
  },
  {
    "year": 2004,
    "pdf_url": "https://www.courts.nh.gov/sites/g/files/ehbemt471/files/documents/2022-05/2004054blackthorne.pdf",
    "case_name": "THE BLACKTHORNE GROUP, INC. v. PINES OF NEWMARKET, INC. MODIFIED MAY 28, 2004",
    "case_number": "2003-401",
    "citation": null,
    "opinion_type": "opinion",
    "date_issued": null,
    "pdf_local_path": "C:\\Users\\gmalb\\Downloads\\nh-supreme-court\\data\\raw\\pdfs\\2004\\2004054blackthorne.pdf"
  },
  {
    "year": 2004,
    "pdf_url": "https://www.courts.nh.gov/sites/g/files/ehbemt471/files/documents/2022-05/2004056boisvert.pdf",
    "case_name": "TOWN OF LYNDEBOROUGH v. BOISVERT PROPERTIES, LLC & a.",
    "case_number": "2003-576",
    "citation": null,
    "opinion_type": "opinion",
    "date_issued": null,
    "pdf_local_path": "C:\\Users\\gmalb\\Downloads\\nh-supreme-court\\data\\raw\\pdfs\\2004\\2004056boisvert.pdf"
  },
  {
    "year": 2004,
    "pdf_url": "https://www.courts.nh.gov/sites/g/files/ehbemt471/files/documents/2022-05/2004053goffstown.pdf",
    "case_name": "PETITION OF GOFFSTOWN EDUCATION SUPPORT STAFF, NEA-NEW HAMPSHIRE",
    "case_number": "2003-370",
    "citation": null,
    "opinion_type": "opinion",
    "date_issued": null,
    "pdf_local_path": "C:\\Users\\gmalb\\Downloads\\nh-supreme-court\\data\\raw\\pdfs\\2004\\2004053goffstown.pdf"
  },
  {
    "year": 2004,
    "pdf_url": "https://www.courts.nh.gov/sites/g/files/ehbemt471/files/documents/2022-05/2004055mccray.pdf",
    "case_name": "TOWN OF MERRIMACK v. DAVID W. MCCRAY (NORMAN CARR, INTERVENOR)",
    "case_number": "2003-484",
    "citation": null,
    "opinion_type": "opinion",
    "date_issued": null,
    "pdf_local_path": "C:\\Users\\gmalb\\Downloads\\nh-supreme-court\\data\\raw\\pdfs\\2004\\2004055mccray.pdf"
  },
  {
    "year": 2004,
    "pdf_url": "https://www.courts.nh.gov/sites/g/files/ehbemt471/files/documents/2022-05/2004050berwick.pdf",
    "case_name": "MOTION MOTORS, INC. v. KENNETH G. BERWICK & a.",
    "case_number": "2003-008",
    "citation": null,
    "opinion_type": "opinion",
    "date_issued": null,
    "pdf_local_path": "C:\\Users\\gmalb\\Downloads\\nh-supreme-court\\data\\raw\\pdfs\\2004\\2004050berwick.pdf"
  },
  {
    "year": 2004,
    "pdf_url": "https://www.courts.nh.gov/sites/g/files/ehbemt471/files/documents/2022-05/2004052anderson.pdf",
    "case_name": "DAVID ANDERSON v. PAULA SMITH",
    "case_number": "2003-266",
    "citation": null,
    "opinion_type": "opinion",
    "date_issued": null,
    "pdf_local_path": "C:\\Users\\gmalb\\Downloads\\nh-supreme-court\\data\\raw\\pdfs\\2004\\2004052anderson.pdf"
  },
  {
    "year": 2004,
    "pdf_url": "https://www.courts.nh.gov/sites/g/files/ehbemt471/files/documents/2022-05/2004051wellington.pdf",
    "case_name": "THE STATE OF NEW HAMPSHIRE v. JAMES WELLINGTON",
    "case_number": "2003-209",
    "citation": null,
    "opinion_type": "opinion",
    "date_issued": null,
    "pdf_local_path": "C:\\Users\\gmalb\\Downloads\\nh-supreme-court\\data\\raw\\pdfs\\2004\\2004051wellington.pdf"
  },
  {
    "year": 2004,
    "pdf_url": "https://www.courts.nh.gov/sites/g/files/ehbemt471/files/documents/2022-05/2004048bennett.pdf",
    "case_name": "TERRY BENNETT v. ITT HARTFORD GROUP, INC. & a.",
    "case_number": "2003-286",
    "citation": null,
    "opinion_type": "opinion",
    "date_issued": null,
    "pdf_local_path": "C:\\Users\\gmalb\\Downloads\\nh-supreme-court\\data\\raw\\pdfs\\2004\\2004048bennett.pdf"
  },
  {
    "year": 2004,
    "pdf_url": "https://www.courts.nh.gov/sites/g/files/ehbemt471/files/documents/2022-05/2004047juvenile.pdf",
    "case_name": "IN RE JUVENILE 2003-248",
    "case_number": "2003-248",
    "citation": null,
    "opinion_type": "opinion",
    "date_issued": null,
    "pdf_local_path": "C:\\Users\\gmalb\\Downloads\\nh-supreme-court\\data\\raw\\pdfs\\2004\\2004047juvenile.pdf"
  },
  {
    "year": 2004,
    "pdf_url": "https://www.courts.nh.gov/sites/g/files/ehbemt471/files/documents/2022-05/2004049motor.pdf",
    "case_name": "NEW HAMPSHIRE MOTOR TRANSPORT ASSOCIATION v. THE STATE OF NEW HAMPSHIRE & a.",
    "case_number": "2003-641",
    "citation": null,
    "opinion_type": "opinion",
    "date_issued": null,
    "pdf_local_path": "C:\\Users\\gmalb\\Downloads\\nh-supreme-court\\data\\raw\\pdfs\\2004\\2004049motor.pdf"
  },
  {
    "year": 2004,
    "pdf_url": "https://www.courts.nh.gov/sites/g/files/ehbemt471/files/documents/2022-05/2004046belton.pdf",
    "case_name": "THE STATE OF NEW HAMPSHIRE v. ALLEN BELTON",
    "case_number": "2003-002",
    "citation": null,
    "opinion_type": "opinion",
    "date_issued": null,
    "pdf_local_path": "C:\\Users\\gmalb\\Downloads\\nh-supreme-court\\data\\raw\\pdfs\\2004\\2004046belton.pdf"
  },
  {
    "year": 2004,
    "pdf_url": "https://www.courts.nh.gov/sites/g/files/ehbemt471/files/documents/2022-05/2004045guarnaccia.pdf",
    "case_name": "2003-272, NEW ENGLAND HOMES, INC. v. R.J. GUARNACCIA IRREVOCABLE TRUST & a.",
    "case_number": "2003-271",
    "citation": null,
    "opinion_type": "opinion",
    "date_issued": null,
    "pdf_local_path": "C:\\Users\\gmalb\\Downloads\\nh-supreme-court\\data\\raw\\pdfs\\2004\\2004045guarnaccia.pdf"
  },
  {
    "year": 2004,
    "pdf_url": "https://www.courts.nh.gov/sites/g/files/ehbemt471/files/documents/2022-05/2004042barnes.pdf",
    "case_name": "THE STATE OF NEW HAMPSHIRE v. DANIEL BARNES - MODIFIED JUNE 10, 2004",
    "case_number": "2003-039",
    "citation": null,
    "opinion_type": "opinion",
    "date_issued": null,
    "pdf_local_path": "C:\\Users\\gmalb\\Downloads\\nh-supreme-court\\data\\raw\\pdfs\\2004\\2004042barnes.pdf"
  },
  {
    "year": 2004,
    "pdf_url": "https://www.courts.nh.gov/sites/g/files/ehbemt471/files/documents/2022-05/2004044sleeper.pdf",
    "case_name": "THE STATE OF NEW HAMPSHIRE v. LAWRENCE SLEEPER",
    "case_number": "2003-254",
    "citation": null,
    "opinion_type": "opinion",
    "date_issued": null,
    "pdf_local_path": "C:\\Users\\gmalb\\Downloads\\nh-supreme-court\\data\\raw\\pdfs\\2004\\2004044sleeper.pdf"
  },
  {
    "year": 2004,
    "pdf_url": "https://www.courts.nh.gov/sites/g/files/ehbemt471/files/documents/2022-05/2004041stern.pdf",
    "case_name": "THE STATE OF NEW HAMPSHIRE v. SHIRLEY ANN STERN",
    "case_number": "2003-307",
    "citation": null,
    "opinion_type": "opinion",
    "date_issued": null,
    "pdf_local_path": "C:\\Users\\gmalb\\Downloads\\nh-supreme-court\\data\\raw\\pdfs\\2004\\2004041stern.pdf"
  },
  {
    "year": 2004,
    "pdf_url": "https://www.courts.nh.gov/sites/g/files/ehbemt471/files/documents/2022-05/2004040arcidi.pdf",
    "case_name": "ALFRED L. ARCIDI, JR. v. TOWN OF RYE",
    "case_number": "2003-238",
    "citation": null,
    "opinion_type": "opinion",
    "date_issued": null,
    "pdf_local_path": "C:\\Users\\gmalb\\Downloads\\nh-supreme-court\\data\\raw\\pdfs\\2004\\2004040arcidi.pdf"
  },
  {
    "year": 2004,
    "pdf_url": "https://www.courts.nh.gov/sites/g/files/ehbemt471/files/documents/2022-05/2004039murnik.pdf",
    "case_name": "LOWER BARTLETT WATER PRECINCT v. RICK MURNIK & a.",
    "case_number": "2004-161",
    "citation": null,
    "opinion_type": "opinion",
    "date_issued": null,
    "pdf_local_path": "C:\\Users\\gmalb\\Downloads\\nh-supreme-court\\data\\raw\\pdfs\\2004\\2004039murnik.pdf"
  },
  {
    "year": 2004,
    "pdf_url": "https://www.courts.nh.gov/sites/g/files/ehbemt471/files/documents/2022-04/2004038pelletier.pdf",
    "case_name": "RICHARD H. PELLETIER v. CITY OF MANCHESTER",
    "case_number": "2003-554",
    "citation": null,
    "opinion_type": "opinion",
    "date_issued": null,
    "pdf_local_path": "C:\\Users\\gmalb\\Downloads\\nh-supreme-court\\data\\raw\\pdfs\\2004\\2004038pelletier.pdf"
  },
  {
    "year": 2004,
    "pdf_url": "https://www.courts.nh.gov/sites/g/files/ehbemt471/files/documents/2022-04/2004037steeplegate.pdf",
    "case_name": "GGP STEEPLEGATE, INC. v. CITY OF CONCORD",
    "case_number": "2003-485",
    "citation": null,
    "opinion_type": "opinion",
    "date_issued": null,
    "pdf_local_path": "C:\\Users\\gmalb\\Downloads\\nh-supreme-court\\data\\raw\\pdfs\\2004\\2004037steeplegate.pdf"
  },
  {
    "year": 2004,
    "pdf_url": "https://www.courts.nh.gov/sites/g/files/ehbemt471/files/documents/2022-04/2004036alexandria.pdf",
    "case_name": "CARY SILVERSTEIN v. TOWN OF ALEXANDRIA",
    "case_number": "2003-388",
    "citation": null,
    "opinion_type": "opinion",
    "date_issued": null,
    "pdf_local_path": "C:\\Users\\gmalb\\Downloads\\nh-supreme-court\\data\\raw\\pdfs\\2004\\2004036alexandria.pdf"
  },
  {
    "year": 2004,
    "pdf_url": "https://www.courts.nh.gov/sites/g/files/ehbemt471/files/documents/2022-04/2004034manchester.pdf",
    "case_name": "CITY OF MANCHESTER SCHOOL DISTRICT & a. v. CITY OF MANCHESTER",
    "case_number": "2003-303",
    "citation": null,
    "opinion_type": "opinion",
    "date_issued": null,
    "pdf_local_path": "C:\\Users\\gmalb\\Downloads\\nh-supreme-court\\data\\raw\\pdfs\\2004\\2004034manchester.pdf"
  },
  {
    "year": 2004,
    "pdf_url": "https://www.courts.nh.gov/sites/g/files/ehbemt471/files/documents/2022-04/2004035crete.pdf",
    "case_name": "CAMBRIDGE MUTUAL FIRE INSURANCE COMPANY & a. v. THOMAS CRETE",
    "case_number": "2003-318",
    "citation": null,
    "opinion_type": "opinion",
    "date_issued": null,
    "pdf_local_path": "C:\\Users\\gmalb\\Downloads\\nh-supreme-court\\data\\raw\\pdfs\\2004\\2004035crete.pdf"
  },
  {
    "year": 2004,
    "pdf_url": "https://www.courts.nh.gov/sites/g/files/ehbemt471/files/documents/2022-04/2004033miller.pdf",
    "case_name": "JOSEPH MILLER v. SLANIA ENTERPRISES, INC.",
    "case_number": "2003-191",
    "citation": null,
    "opinion_type": "opinion",
    "date_issued": null,
    "pdf_local_path": "C:\\Users\\gmalb\\Downloads\\nh-supreme-court\\data\\raw\\pdfs\\2004\\2004033miller.pdf"
  },
  {
    "year": 2004,
    "pdf_url": "https://www.courts.nh.gov/sites/g/files/ehbemt471/files/documents/2022-04/2004031juvenile.pdf",
    "case_name": "IN RE JUVENILE 2003-195",
    "case_number": "2003-195",
    "citation": null,
    "opinion_type": "opinion",
    "date_issued": null,
    "pdf_local_path": "C:\\Users\\gmalb\\Downloads\\nh-supreme-court\\data\\raw\\pdfs\\2004\\2004031juvenile.pdf"
  },
  {
    "year": 2004,
    "pdf_url": "https://www.courts.nh.gov/sites/g/files/ehbemt471/files/documents/2022-04/2004029sandra.pdf",
    "case_name": "In re SANDRA H.",
    "case_number": "2003-020",
    "citation": null,
    "opinion_type": "opinion",
    "date_issued": null,
    "pdf_local_path": "C:\\Users\\gmalb\\Downloads\\nh-supreme-court\\data\\raw\\pdfs\\2004\\2004029sandra.pdf"
  },
  {
    "year": 2004,
    "pdf_url": "https://www.courts.nh.gov/sites/g/files/ehbemt471/files/documents/2022-04/2004032howard.pdf",
    "case_name": "REMINGTON INVESTMENTS, INC. v. GARY A. HOWARD",
    "case_number": "2003-431",
    "citation": null,
    "opinion_type": "opinion",
    "date_issued": null,
    "pdf_local_path": "C:\\Users\\gmalb\\Downloads\\nh-supreme-court\\data\\raw\\pdfs\\2004\\2004032howard.pdf"
  },
  {
    "year": 2004,
    "pdf_url": "https://www.courts.nh.gov/sites/g/files/ehbemt471/files/documents/2022-04/2004030gatchell.pdf",
    "case_name": "THE STATE OF NEW HAMPSHIRE v. PAUL B. GATCHELL",
    "case_number": "2003-070",
    "citation": null,
    "opinion_type": "opinion",
    "date_issued": null,
    "pdf_local_path": "C:\\Users\\gmalb\\Downloads\\nh-supreme-court\\data\\raw\\pdfs\\2004\\2004030gatchell.pdf"
  },
  {
    "year": 2004,
    "pdf_url": "https://www.courts.nh.gov/sites/g/files/ehbemt471/files/documents/2022-04/2004028jerome.pdf",
    "case_name": "IN THE MATTER OF TONI E. JEROME AND RAYMOND W. JEROME",
    "case_number": "2003-380",
    "citation": null,
    "opinion_type": "opinion",
    "date_issued": null,
    "pdf_local_path": "C:\\Users\\gmalb\\Downloads\\nh-supreme-court\\data\\raw\\pdfs\\2004\\2004028jerome.pdf"
  },
  {
    "year": 2004,
    "pdf_url": "https://www.courts.nh.gov/sites/g/files/ehbemt471/files/documents/2022-04/2004027fox.pdf",
    "case_name": "THE STATE OF NEW HAMPSHIRE v. EARLE K. FOX, III",
    "case_number": "2003-032",
    "citation": null,
    "opinion_type": "opinion",
    "date_issued": null,
    "pdf_local_path": "C:\\Users\\gmalb\\Downloads\\nh-supreme-court\\data\\raw\\pdfs\\2004\\2004027fox.pdf"
  },
  {
    "year": 2004,
    "pdf_url": "https://www.courts.nh.gov/sites/g/files/ehbemt471/files/documents/2022-04/2004026bethlehem.pdf",
    "case_name": "NORTH COUNTRY ENVIRONMENTAL SERVICES, INC. v. TOWN OF BETHLEHEM & a.",
    "case_number": "2003-337",
    "citation": null,
    "opinion_type": "opinion",
    "date_issued": null,
    "pdf_local_path": "C:\\Users\\gmalb\\Downloads\\nh-supreme-court\\data\\raw\\pdfs\\2004\\2004026bethlehem.pdf"
  },
  {
    "year": 2004,
    "pdf_url": "https://www.courts.nh.gov/sites/g/files/ehbemt471/files/documents/2022-04/2004023velez.pdf",
    "case_name": "THE STATE OF NEW HAMPSHIRE v. DENIS VELEZ",
    "case_number": "2003-078",
    "citation": null,
    "opinion_type": "opinion",
    "date_issued": null,
    "pdf_local_path": "C:\\Users\\gmalb\\Downloads\\nh-supreme-court\\data\\raw\\pdfs\\2004\\2004023velez.pdf"
  },
  {
    "year": 2004,
    "pdf_url": "https://www.courts.nh.gov/sites/g/files/ehbemt471/files/documents/2022-04/2004024generallinen.pdf",
    "case_name": "GENERAL LINEN SERVICES, INC. v. FRANCONIA INVESTMENT ASSOCIATES, L.P. & a.",
    "case_number": "2003-177",
    "citation": null,
    "opinion_type": "opinion",
    "date_issued": null,
    "pdf_local_path": "C:\\Users\\gmalb\\Downloads\\nh-supreme-court\\data\\raw\\pdfs\\2004\\2004024generallinen.pdf"
  },
  {
    "year": 2004,
    "pdf_url": "https://www.courts.nh.gov/sites/g/files/ehbemt471/files/documents/2022-04/2004022kersey.pdf",
    "case_name": "LD-2002-006, KERSEY'S CASE",
    "case_number": null,
    "citation": null,
    "opinion_type": "opinion",
    "date_issued": null,
    "pdf_local_path": "C:\\Users\\gmalb\\Downloads\\nh-supreme-court\\data\\raw\\pdfs\\2004\\2004022kersey.pdf"
  },
  {
    "year": 2004,
    "pdf_url": "https://www.courts.nh.gov/sites/g/files/ehbemt471/files/documents/2022-04/2004025kidder.pdf",
    "case_name": "THE STATE OF NEW HAMPSHIRE v. STEVEN KIDDER",
    "case_number": "2003-362",
    "citation": null,
    "opinion_type": "opinion",
    "date_issued": null,
    "pdf_local_path": "C:\\Users\\gmalb\\Downloads\\nh-supreme-court\\data\\raw\\pdfs\\2004\\2004025kidder.pdf"
  },
  {
    "year": 2004,
    "pdf_url": "https://www.courts.nh.gov/sites/g/files/ehbemt471/files/documents/2022-04/2004021hawkeye.pdf",
    "case_name": "DUKE/FLUOR DANIEL v. HAWKEYE FUNDING, LIMITED PARTNERSHIP & a.",
    "case_number": "2003-173",
    "citation": null,
    "opinion_type": "opinion",
    "date_issued": null,
    "pdf_local_path": "C:\\Users\\gmalb\\Downloads\\nh-supreme-court\\data\\raw\\pdfs\\2004\\2004021hawkeye.pdf"
  },
  {
    "year": 2004,
    "pdf_url": "https://www.courts.nh.gov/sites/g/files/ehbemt471/files/documents/2022-04/2004020swain.pdf",
    "case_name": "SHERRY SWAIN v. EMPLOYERS MUTUAL CASUALTY COMPANY",
    "case_number": "2003-245",
    "citation": null,
    "opinion_type": "opinion",
    "date_issued": null,
    "pdf_local_path": "C:\\Users\\gmalb\\Downloads\\nh-supreme-court\\data\\raw\\pdfs\\2004\\2004020swain.pdf"
  },
  {
    "year": 2004,
    "pdf_url": "https://www.courts.nh.gov/sites/g/files/ehbemt471/files/documents/2022-04/2004019nelson.pdf",
    "case_name": "THE STATE OF NEW HAMPSHIRE v. ROBERT W. NELSON",
    "case_number": "2003-162",
    "citation": null,
    "opinion_type": "opinion",
    "date_issued": null,
    "pdf_local_path": "C:\\Users\\gmalb\\Downloads\\nh-supreme-court\\data\\raw\\pdfs\\2004\\2004019nelson.pdf"
  },
  {
    "year": 2004,
    "pdf_url": "https://www.courts.nh.gov/sites/g/files/ehbemt471/files/documents/2022-04/2004018oliva.pdf",
    "case_name": "STEPHEN S. OLIVA v. VERMONT MUTUAL INSURANCE COMPANY & a.",
    "case_number": "2003-316",
    "citation": null,
    "opinion_type": "opinion",
    "date_issued": null,
    "pdf_local_path": "C:\\Users\\gmalb\\Downloads\\nh-supreme-court\\data\\raw\\pdfs\\2004\\2004018oliva.pdf"
  },
  {
    "year": 2004,
    "pdf_url": "https://www.courts.nh.gov/sites/g/files/ehbemt471/files/documents/2022-04/2004016gronvaldt.pdf",
    "case_name": "IN THE MATTER OF JESPER GRONVALDT AND CLAUDIA GRONVALDT",
    "case_number": "2003-132",
    "citation": null,
    "opinion_type": "opinion",
    "date_issued": null,
    "pdf_local_path": "C:\\Users\\gmalb\\Downloads\\nh-supreme-court\\data\\raw\\pdfs\\2004\\2004016gronvaldt.pdf"
  },
  {
    "year": 2004,
    "pdf_url": "https://www.courts.nh.gov/sites/g/files/ehbemt471/files/documents/2022-04/2004017lyme.pdf",
    "case_name": "THE LYME TIMBER COMPANY & a. v. DSF INVESTORS LLC & a.",
    "case_number": "2003-312",
    "citation": null,
    "opinion_type": "opinion",
    "date_issued": null,
    "pdf_local_path": "C:\\Users\\gmalb\\Downloads\\nh-supreme-court\\data\\raw\\pdfs\\2004\\2004017lyme.pdf"
  },
  {
    "year": 2004,
    "pdf_url": "https://www.courts.nh.gov/sites/g/files/ehbemt471/files/documents/2022-04/2004015merriam.pdf",
    "case_name": "THE STATE OF NEW HAMPSHIRE v. STEPHEN MERRIAM",
    "case_number": "2003-273",
    "citation": null,
    "opinion_type": "opinion",
    "date_issued": null,
    "pdf_local_path": "C:\\Users\\gmalb\\Downloads\\nh-supreme-court\\data\\raw\\pdfs\\2004\\2004015merriam.pdf"
  },
  {
    "year": 2004,
    "pdf_url": "https://www.courts.nh.gov/sites/g/files/ehbemt471/files/documents/2022-04/2004013scognamiglio.pdf",
    "case_name": "THE STATE OF NEW HAMPSHIRE v. CIRO SCOGNAMIGLIO",
    "case_number": "2002-785",
    "citation": null,
    "opinion_type": "opinion",
    "date_issued": null,
    "pdf_local_path": "C:\\Users\\gmalb\\Downloads\\nh-supreme-court\\data\\raw\\pdfs\\2004\\2004013scognamiglio.pdf"
  },
  {
    "year": 2004,
    "pdf_url": "https://www.courts.nh.gov/sites/g/files/ehbemt471/files/documents/2022-04/2004014gutbier.pdf",
    "case_name": "MARIANNE GUTBIER v. HANNAFORD BROTHERS CO. D/B/A HOOKSETT SHOP 'N SAVE",
    "case_number": "2003-236",
    "citation": null,
    "opinion_type": "opinion",
    "date_issued": null,
    "pdf_local_path": "C:\\Users\\gmalb\\Downloads\\nh-supreme-court\\data\\raw\\pdfs\\2004\\2004014gutbier.pdf"
  },
  {
    "year": 2004,
    "pdf_url": "https://www.courts.nh.gov/sites/g/files/ehbemt471/files/documents/2022-04/2004011barrett.pdf",
    "case_name": "IN THE MATTER OF SUSAN C. BARRETT AND JOHN T. COYNE",
    "case_number": "2003-101",
    "citation": null,
    "opinion_type": "opinion",
    "date_issued": null,
    "pdf_local_path": "C:\\Users\\gmalb\\Downloads\\nh-supreme-court\\data\\raw\\pdfs\\2004\\2004011barrett.pdf"
  },
  {
    "year": 2004,
    "pdf_url": "https://www.courts.nh.gov/sites/g/files/ehbemt471/files/documents/2022-04/2004012statefarm.pdf",
    "case_name": "STATE FARM MUTUAL AUTOMOBILE INSURANCE COMPANY v. HOLYOKE MUTUAL INSURANCE COMPANY & a.",
    "case_number": "2003-213",
    "citation": null,
    "opinion_type": "opinion",
    "date_issued": null,
    "pdf_local_path": "C:\\Users\\gmalb\\Downloads\\nh-supreme-court\\data\\raw\\pdfs\\2004\\2004012statefarm.pdf"
  },
  {
    "year": 2004,
    "pdf_url": "https://www.courts.nh.gov/sites/g/files/ehbemt471/files/documents/2022-04/2004008giacomini.pdf",
    "case_name": "IN THE MATTER OF BARBARA M. GIACOMINI AND PATRICK A. GIACOMINI",
    "case_number": "2002-716",
    "citation": null,
    "opinion_type": "opinion",
    "date_issued": null,
    "pdf_local_path": "C:\\Users\\gmalb\\Downloads\\nh-supreme-court\\data\\raw\\pdfs\\2004\\2004008giacomini.pdf"
  },
  {
    "year": 2004,
    "pdf_url": "https://www.courts.nh.gov/sites/g/files/ehbemt471/files/documents/2022-04/2004010jacobson.pdf",
    "case_name": "IN THE MATTER OF ROBERT JACOBSON AND KATHLEEN TIERNEY",
    "case_number": "2003-093",
    "citation": null,
    "opinion_type": "opinion",
    "date_issued": null,
    "pdf_local_path": "C:\\Users\\gmalb\\Downloads\\nh-supreme-court\\data\\raw\\pdfs\\2004\\2004010jacobson.pdf"
  },
  {
    "year": 2004,
    "pdf_url": "https://www.courts.nh.gov/sites/g/files/ehbemt471/files/documents/2022-04/2004007laconia.pdf",
    "case_name": "APPEAL OF LACONIA SCHOOL DISTRICT (New Hampshire Public Employee Labor Relations Board)",
    "case_number": "2002-670",
    "citation": null,
    "opinion_type": "opinion",
    "date_issued": null,
    "pdf_local_path": "C:\\Users\\gmalb\\Downloads\\nh-supreme-court\\data\\raw\\pdfs\\2004\\2004007laconia.pdf"
  },
  {
    "year": 2004,
    "pdf_url": "https://www.courts.nh.gov/sites/g/files/ehbemt471/files/documents/2022-04/2004005bacon.pdf",
    "case_name": "MAUREEN BACON v. TOWN OF ENFIELD",
    "case_number": "2002-591",
    "citation": null,
    "opinion_type": "opinion",
    "date_issued": null,
    "pdf_local_path": "C:\\Users\\gmalb\\Downloads\\nh-supreme-court\\data\\raw\\pdfs\\2004\\2004005bacon.pdf"
  },
  {
    "year": 2004,
    "pdf_url": "https://www.courts.nh.gov/sites/g/files/ehbemt471/files/documents/2022-04/2004006rezk.pdf",
    "case_name": "THE STATE OF NEW HAMPSHIRE v. MICHAEL REZK",
    "case_number": "2002-618",
    "citation": null,
    "opinion_type": "opinion",
    "date_issued": null,
    "pdf_local_path": "C:\\Users\\gmalb\\Downloads\\nh-supreme-court\\data\\raw\\pdfs\\2004\\2004006rezk.pdf"
  },
  {
    "year": 2004,
    "pdf_url": "https://www.courts.nh.gov/sites/g/files/ehbemt471/files/documents/2022-04/2004004reno.pdf",
    "case_name": "THE STATE OF NEW HAMPSHIRE v. DAVID RENO",
    "case_number": "2003-152",
    "citation": null,
    "opinion_type": "opinion",
    "date_issued": null,
    "pdf_local_path": "C:\\Users\\gmalb\\Downloads\\nh-supreme-court\\data\\raw\\pdfs\\2004\\2004004reno.pdf"
  },
  {
    "year": 2004,
    "pdf_url": "https://www.courts.nh.gov/sites/g/files/ehbemt471/files/documents/2022-04/2004003small.pdf",
    "case_name": "THE STATE OF NEW HAMPSHIRE v. DANIEL SMALL",
    "case_number": "2002-592",
    "citation": null,
    "opinion_type": "opinion",
    "date_issued": null,
    "pdf_local_path": "C:\\Users\\gmalb\\Downloads\\nh-supreme-court\\data\\raw\\pdfs\\2004\\2004003small.pdf"
  },
  {
    "year": 2004,
    "pdf_url": "https://www.courts.nh.gov/sites/g/files/ehbemt471/files/documents/2022-04/2004002johnston.pdf",
    "case_name": "STATE OF NEW HAMPSHIRE v. JAMES JOHNSTON, JR.",
    "case_number": "2003-232",
    "citation": null,
    "opinion_type": "opinion",
    "date_issued": null,
    "pdf_local_path": "C:\\Users\\gmalb\\Downloads\\nh-supreme-court\\data\\raw\\pdfs\\2004\\2004002johnston.pdf"
  },
  {
    "year": 2004,
    "pdf_url": "https://www.courts.nh.gov/sites/g/files/ehbemt471/files/documents/2022-04/2004001barka.pdf",
    "case_name": "2002-384; 2002-390; 2002-643, IN RE GRAND JURY SUBPOENA FOR MEDICAL RECORDS OF CURTIS PAYNE; IN RE GRAND JURY SUBPOENA FOR MEDICAL RECORDS OF SCOTT CARTA; THE STATE OF NEW HAMPSHIRE v. GREGORY BARKA",
    "case_number": null,
    "citation": null,
    "opinion_type": "opinion",
    "date_issued": null,
    "pdf_local_path": "C:\\Users\\gmalb\\Downloads\\nh-supreme-court\\data\\raw\\pdfs\\2004\\2004001barka.pdf"
  },
  {
    "year": 2004,
    "pdf_url": "https://www.courts.nh.gov/sites/g/files/ehbemt471/files/documents/2022-05/2004043cherry.pdf",
    "case_name": "ERNEST M. CHERRY, JR. & a. v. TOWN OF HAMPTON FALLS & a.",
    "case_number": "2003-121",
    "citation": null,
    "opinion_type": "opinion",
    "date_issued": null,
    "pdf_local_path": "C:\\Users\\gmalb\\Downloads\\nh-supreme-court\\data\\raw\\pdfs\\2004\\2004043cherry.pdf"
  },
  {
    "year": 2004,
    "pdf_url": "https://www.courts.nh.gov/sites/g/files/ehbemt471/files/documents/2022-06/2004105wiggin.pdf",
    "case_name": "STATE OF NH v. JOHN D. WIGGIN",
    "case_number": "2003-628",
    "citation": null,
    "opinion_type": "opinion",
    "date_issued": null,
    "pdf_local_path": "C:\\Users\\gmalb\\Downloads\\nh-supreme-court\\data\\raw\\pdfs\\2004\\2004105wiggin.pdf"
  },
  {
    "year": 2004,
    "pdf_url": "https://www.courts.nh.gov/sites/g/files/ehbemt471/files/documents/2022-06/2004103letarte.pdf",
    "case_name": "HANK LETARTE v. WEST SIDE DEVELOPMENT GROUP, LLC",
    "case_number": "2003-0830",
    "citation": null,
    "opinion_type": "opinion",
    "date_issued": null,
    "pdf_local_path": "C:\\Users\\gmalb\\Downloads\\nh-supreme-court\\data\\raw\\pdfs\\2004\\2004103letarte.pdf"
  },
  {
    "year": 2004,
    "pdf_url": "https://www.courts.nh.gov/sites/g/files/ehbemt471/files/documents/2022-06/2004109simone.pdf",
    "case_name": "STATE OF NH v. FRANK SIMONE",
    "case_number": "2003-427",
    "citation": null,
    "opinion_type": "opinion",
    "date_issued": null,
    "pdf_local_path": "C:\\Users\\gmalb\\Downloads\\nh-supreme-court\\data\\raw\\pdfs\\2004\\2004109simone.pdf"
  },
  {
    "year": 2004,
    "pdf_url": "https://www.courts.nh.gov/sites/g/files/ehbemt471/files/documents/2022-06/2004125lorenz.pdf",
    "case_name": "PATRICK J. LORENZ & a. v. NEW HAMPSHIRE ADMINISTRATIVE OFFICE OF THE COURTS & a.",
    "case_number": "2004-552",
    "citation": null,
    "opinion_type": "opinion",
    "date_issued": null,
    "pdf_local_path": "C:\\Users\\gmalb\\Downloads\\nh-supreme-court\\data\\raw\\pdfs\\2004\\2004125lorenz.pdf"
  },
  {
    "year": 2004,
    "pdf_url": "https://www.courts.nh.gov/sites/g/files/ehbemt471/files/documents/2022-06/2004107saviano.pdf",
    "case_name": "MICHAEL SAVIANO v. DIRECTOR, NH DIVISION OF MOTOR VEHICLES",
    "case_number": "2003-772",
    "citation": null,
    "opinion_type": "opinion",
    "date_issued": null,
    "pdf_local_path": "C:\\Users\\gmalb\\Downloads\\nh-supreme-court\\data\\raw\\pdfs\\2004\\2004107saviano.pdf"
  },
  {
    "year": 2004,
    "pdf_url": "https://www.courts.nh.gov/sites/g/files/ehbemt471/files/documents/2022-06/2004111fireworks.pdf",
    "case_name": "APPEAL OF NEW HAMPSHIRE FIREWORKS, INC.",
    "case_number": "2003-589",
    "citation": null,
    "opinion_type": "opinion",
    "date_issued": null,
    "pdf_local_path": "C:\\Users\\gmalb\\Downloads\\nh-supreme-court\\data\\raw\\pdfs\\2004\\2004111fireworks.pdf"
  },
  {
    "year": 2004,
    "pdf_url": "https://www.courts.nh.gov/sites/g/files/ehbemt471/files/documents/2022-06/2004104sousa.pdf",
    "case_name": "STATE OF NH v. CHRISTINE SOUSA",
    "case_number": "2003-552",
    "citation": null,
    "opinion_type": "opinion",
    "date_issued": null,
    "pdf_local_path": "C:\\Users\\gmalb\\Downloads\\nh-supreme-court\\data\\raw\\pdfs\\2004\\2004104sousa.pdf"
  },
  {
    "year": 2004,
    "pdf_url": "https://www.courts.nh.gov/sites/g/files/ehbemt471/files/documents/2022-06/2004113cossette.pdf",
    "case_name": "STATE OF NH v. THOMAS P. COSSETTE",
    "case_number": "2003-142",
    "citation": null,
    "opinion_type": "opinion",
    "date_issued": null,
    "pdf_local_path": "C:\\Users\\gmalb\\Downloads\\nh-supreme-court\\data\\raw\\pdfs\\2004\\2004113cossette.pdf"
  },
  {
    "year": 2004,
    "pdf_url": "https://www.courts.nh.gov/sites/g/files/ehbemt471/files/documents/2022-06/2004102moore.pdf",
    "case_name": "THE STATE OF NH v. DEBORAH MOORE",
    "case_number": "2003-0544",
    "citation": null,
    "opinion_type": "opinion",
    "date_issued": null,
    "pdf_local_path": "C:\\Users\\gmalb\\Downloads\\nh-supreme-court\\data\\raw\\pdfs\\2004\\2004102moore.pdf"
  },
  {
    "year": 2004,
    "pdf_url": "https://www.courts.nh.gov/sites/g/files/ehbemt471/files/documents/2022-06/2004106chace.pdf",
    "case_name": "THE STATE OF NH v. KRISTEN CHACE",
    "case_number": "2003-682",
    "citation": null,
    "opinion_type": "opinion",
    "date_issued": null,
    "pdf_local_path": "C:\\Users\\gmalb\\Downloads\\nh-supreme-court\\data\\raw\\pdfs\\2004\\2004106chace.pdf"
  },
  {
    "year": 2004,
    "pdf_url": "https://www.courts.nh.gov/sites/g/files/ehbemt471/files/documents/2022-06/2004115gordonville.pdf",
    "case_name": "GORDONVILLE CORPORATION N.V. v. LR1-A LIMITED PARTNERSHIP",
    "case_number": "2004-023",
    "citation": null,
    "opinion_type": "opinion",
    "date_issued": null,
    "pdf_local_path": "C:\\Users\\gmalb\\Downloads\\nh-supreme-court\\data\\raw\\pdfs\\2004\\2004115gordonville.pdf"
  },
  {
    "year": 2004,
    "pdf_url": "https://www.courts.nh.gov/sites/g/files/ehbemt471/files/documents/2022-06/2004110morrill.pdf",
    "case_name": "STATE OF NH v. DONALD MORRILL A/K/A SAM W. MORRILL",
    "case_number": "2003-654",
    "citation": null,
    "opinion_type": "opinion",
    "date_issued": null,
    "pdf_local_path": "C:\\Users\\gmalb\\Downloads\\nh-supreme-court\\data\\raw\\pdfs\\2004\\2004110morrill.pdf"
  },
  {
    "year": 2004,
    "pdf_url": "https://www.courts.nh.gov/sites/g/files/ehbemt471/files/documents/2022-06/2004118marikar.pdf",
    "case_name": "YVONNE MARIKAR v. PEERLESS INSURANCE COMPANY",
    "case_number": "2003-701",
    "citation": null,
    "opinion_type": "opinion",
    "date_issued": null,
    "pdf_local_path": "C:\\Users\\gmalb\\Downloads\\nh-supreme-court\\data\\raw\\pdfs\\2004\\2004118marikar.pdf"
  },
  {
    "year": 2004,
    "pdf_url": "https://www.courts.nh.gov/sites/g/files/ehbemt471/files/documents/2022-06/2004101roldan.pdf",
    "case_name": "THE STATE OF NH v. ANGEL ROLDAN",
    "case_number": "2002-0743",
    "citation": null,
    "opinion_type": "opinion",
    "date_issued": null,
    "pdf_local_path": "C:\\Users\\gmalb\\Downloads\\nh-supreme-court\\data\\raw\\pdfs\\2004\\2004101roldan.pdf"
  },
  {
    "year": 2004,
    "pdf_url": "https://www.courts.nh.gov/sites/g/files/ehbemt471/files/documents/2022-06/2004112mcnair.pdf",
    "case_name": "HEIDI MCNAIR v. RYAN MCNAIR",
    "case_number": "2003-704",
    "citation": null,
    "opinion_type": "opinion",
    "date_issued": null,
    "pdf_local_path": "C:\\Users\\gmalb\\Downloads\\nh-supreme-court\\data\\raw\\pdfs\\2004\\2004112mcnair.pdf"
  }
]